langchain_luma/__init__.py
langchain_luma/client.py
langchain_luma/documents.py
langchain_luma/errors.py
langchain_luma/exceptions.py
langchain_luma/http.py
langchain_luma/rag.py
langchain_luma/server.py
langchain_luma/sql.py
langchain_luma/state.py
langchain_luma/stream.py
langchain_luma/system.py
langchain_luma/utils.py
langchain_luma/validators.py
langchain_luma/vectors.py
langchain_luma/bin/luma-linux-amd64
langchain_luma/bin/luma-macos-amd64
langchain_luma/bin/luma-windows-amd64.exe
langchain_luma/langchain/__init__.py
langchain_luma/langchain/vectorstore.py
langchain_luma-1.1.2.dist-info/licenses/LICENSE
langchain_luma-1.1.2.dist-info/METADATA
langchain_luma-1.1.2.dist-info/WHEEL
langchain_luma-1.1.2.dist-info/top_level.txt
langchain_luma-1.1.2.dist-info/RECORD
