Metadata-Version: 2.4
Name: langchain_luma
Version: 1.1.2
Summary: Python Client SDK for Luma (RustKissVDB)
Author-email: Jairo Mendoza <jairodaniel.mt@gmail.com>
Project-URL: Homepage, https://github.com/example/langchain_luma
Project-URL: Bug Tracker, https://github.com/example/langchain_luma/issues
Classifier: Programming Language :: Python :: 3
Classifier: Programming Language :: Python :: 3.11
Classifier: Programming Language :: Python :: 3.12
Classifier: License :: OSI Approved :: MIT License
Classifier: Operating System :: OS Independent
Requires-Python: >=3.11
License-File: LICENSE
Requires-Dist: langchain-core>=1.2.7
Requires-Dist: pytest>=9.0.2
Requires-Dist: requests>=2.31.0
Provides-Extra: langchain
Requires-Dist: langchain-core; extra == "langchain"
Requires-Dist: langchain-community; extra == "langchain"
Provides-Extra: dev
Requires-Dist: pytest>=7.0; extra == "dev"
Requires-Dist: ruff>=0.1.0; extra == "dev"
Requires-Dist: build; extra == "dev"
Requires-Dist: twine; extra == "dev"
Dynamic: license-file
